{
  "src/routes/+layout.css": {
    "file": "_app/immutable/assets/_layout-c3750300.css",
    "src": "src/routes/+layout.css"
  },
  "_singletons-c1679a6a.js": {
    "file": "_app/immutable/chunks/singletons-c1679a6a.js",
    "imports": [
      "_index-4c4c63a2.js"
    ]
  },
  ".svelte-kit/generated/nodes/2.js": {
    "file": "_app/immutable/chunks/2-93296db8.js",
    "src": ".svelte-kit/generated/nodes/2.js",
    "isDynamicEntry": true,
    "imports": [
      "src/routes/+page.svelte"
    ]
  },
  ".svelte-kit/generated/nodes/3.js": {
    "file": "_app/immutable/chunks/3-53010a0c.js",
    "src": ".svelte-kit/generated/nodes/3.js",
    "isDynamicEntry": true,
    "imports": [
      "src/routes/[slug]/+page.svelte"
    ]
  },
  ".svelte-kit/generated/nodes/1.js": {
    "file": "_app/immutable/chunks/1-1d3276ce.js",
    "src": ".svelte-kit/generated/nodes/1.js",
    "isDynamicEntry": true,
    "imports": [
      "node_modules/@sveltejs/kit/src/runtime/components/error.svelte"
    ]
  },
  ".svelte-kit/generated/nodes/4.js": {
    "file": "_app/immutable/chunks/4-4299fb3a.js",
    "src": ".svelte-kit/generated/nodes/4.js",
    "isDynamicEntry": true,
    "imports": [
      "src/routes/about/+page.svelte"
    ]
  },
  "src/routes/[slug]/+page.svelte": {
    "file": "_app/immutable/components/pages/_slug_/_page.svelte-e4919474.js",
    "src": "src/routes/[slug]/+page.svelte",
    "isEntry": true,
    "imports": [
      "_index-4c4c63a2.js"
    ]
  },
  "node_modules/@sveltejs/kit/src/runtime/components/error.svelte": {
    "file": "_app/immutable/components/error.svelte-f9d5fd2b.js",
    "src": "node_modules/@sveltejs/kit/src/runtime/components/error.svelte",
    "isEntry": true,
    "imports": [
      "_index-4c4c63a2.js",
      "_singletons-c1679a6a.js"
    ]
  },
  "src/routes/+page.svelte": {
    "file": "_app/immutable/components/pages/_page.svelte-2c5a9b11.js",
    "src": "src/routes/+page.svelte",
    "isEntry": true,
    "imports": [
      "_index-4c4c63a2.js"
    ]
  },
  ".svelte-kit/generated/nodes/0.js": {
    "file": "_app/immutable/chunks/0-088d62d7.js",
    "src": ".svelte-kit/generated/nodes/0.js",
    "isDynamicEntry": true,
    "imports": [
      "src/routes/+layout.svelte"
    ]
  },
  "src/routes/about/+page.svelte": {
    "file": "_app/immutable/components/pages/about/_page.svelte-8715ce1e.js",
    "src": "src/routes/about/+page.svelte",
    "isEntry": true,
    "imports": [
      "_index-4c4c63a2.js"
    ]
  },
  "_index-4c4c63a2.js": {
    "file": "_app/immutable/chunks/index-4c4c63a2.js"
  },
  "src/routes/+layout.svelte": {
    "file": "_app/immutable/components/pages/_layout.svelte-f27464bc.js",
    "src": "src/routes/+layout.svelte",
    "isEntry": true,
    "imports": [
      "_index-4c4c63a2.js"
    ],
    "css": [
      "_app/immutable/assets/_layout-c3750300.css"
    ]
  },
  "node_modules/@sveltejs/kit/src/runtime/client/start.js": {
    "file": "_app/immutable/start-3b9ce475.js",
    "src": "node_modules/@sveltejs/kit/src/runtime/client/start.js",
    "isEntry": true,
    "imports": [
      "_index-4c4c63a2.js",
      "_singletons-c1679a6a.js"
    ],
    "dynamicImports": [
      ".svelte-kit/generated/nodes/0.js",
      ".svelte-kit/generated/nodes/1.js",
      ".svelte-kit/generated/nodes/2.js",
      ".svelte-kit/generated/nodes/3.js",
      ".svelte-kit/generated/nodes/4.js"
    ]
  }
}